pywellgeo/__init__.py
pywellgeo/transformations/__init__.py
pywellgeo/transformations/azim_dip.py
pywellgeo/transformations/coordinate_transformation.py
pywellgeo/well_data/__init__.py
pywellgeo/well_data/dc1dwell.py
pywellgeo/well_data/names_constants.py
pywellgeo/well_data/water_properties.py
pywellgeo/well_tree/__init__.py
pywellgeo/well_tree/well_tree_azim_dip.py
pywellgeo/well_tree/well_tree_tno.py
pywellgeo/welltrajectory/__init__.py
pywellgeo/welltrajectory/trajectory.py
pywellgeo/welltrajectory/trajectory_base.py
pywellgeo/welltrajectory/trajectory_dc1d.py
pywellgeo/welltrajectory/trajectory_detailed_tno.py
pywellgeo/welltrajectory/trajectory_factory.py
pywellgeo/welltrajectory/trajectory_xyz_generic.py
pywellgeo-0.1.1.dist-info/licenses/LICENSE
pywellgeo-0.1.1.dist-info/METADATA
pywellgeo-0.1.1.dist-info/WHEEL
pywellgeo-0.1.1.dist-info/top_level.txt
pywellgeo-0.1.1.dist-info/RECORD
