Metadata-Version: 2.4
Name: pywellgeo
Version: 0.1.1
Summary: Different well parametrizations used in pywellfast and pythermonomics
Author-email: Stephan de Hoop <stephan.dehoop@tno.nl>
License:                     GNU GENERAL PUBLIC LICENSE
Project-URL: Homepage, https://github.com/TNO/pywellgeo
Project-URL: Repository, https://github.com/TNO/pywellgeo
Project-URL: Issues, https://github.com/TNO/pywellgeo/issues
Keywords: well,geothermal,reservoir,simulation,engineering
Classifier: Programming Language :: Python :: 3
Classifier: Programming Language :: Python :: 3 :: Only
Classifier: Programming Language :: Python :: 3.11
Classifier: Programming Language :: Python :: 3.12
Classifier: License :: OSI Approved :: GNU General Public License v3 (GPLv3)
Classifier: Operating System :: OS Independent
Classifier: Intended Audience :: Science/Research
Classifier: Topic :: Scientific/Engineering
Requires-Python: >=3.11
License-File: LICENSE
Requires-Dist: numpy
Requires-Dist: pandas
Requires-Dist: pydantic
Requires-Dist: pyyaml
Requires-Dist: matplotlib
Requires-Dist: scipy
Provides-Extra: tests
Requires-Dist: pytest; extra == "tests"
Provides-Extra: docs
Requires-Dist: mkdocs; extra == "docs"
Requires-Dist: mkdocstrings[python]; extra == "docs"
Requires-Dist: mkdocs-material; extra == "docs"
Requires-Dist: mike; extra == "docs"
Dynamic: license-file
